txboto3/__init__.py
txboto3/client.py
txboto3/tests/__init__.py
txboto3/tests/test_client.py
txboto3-0.1.1.dist-info/METADATA
txboto3-0.1.1.dist-info/WHEEL
txboto3-0.1.1.dist-info/RECORD
