Metadata-Version: 2.1
Name: txboto3
Version: 0.1.1
Summary: Run Boto3 in Twisted withotut blocking
Author: Brenno Almeida
Author-email: contato@brennoflavio.com.br
Requires-Python: >=3.10,<4.0
Classifier: Programming Language :: Python :: 3
Classifier: Programming Language :: Python :: 3.10
Classifier: Programming Language :: Python :: 3.11
Requires-Dist: boto3 (>=1.14.7,<2.0.0)
Requires-Dist: twisted (>=24.3.0,<25.0.0)
